esy/osmfilter/__init__.py
esy/osmfilter/element_filter.py
esy/osmfilter/geojson.py
esy/osmfilter/osm_colors.py
esy/osmfilter/osm_filter.py
esy/osmfilter/osm_info.py
esy/osmfilter/osm_pickle.py
esy/osmfilter/osmformat_pb2.py
esy/osmfilter/pre_filter.py
esy_osmfilter-1.0.11.dist-info/LICENSE
esy_osmfilter-1.0.11.dist-info/METADATA
esy_osmfilter-1.0.11.dist-info/WHEEL
esy_osmfilter-1.0.11.dist-info/top_level.txt
esy_osmfilter-1.0.11.dist-info/RECORD
