Metadata-Version: 2.1
Name: esy-osmfilter
Version: 1.0.11
Summary: Filtering of OSM pbf-files and exporting to geojson
Home-page: https://github.com/pypa/osmfilter
Author: Adam Pluta
Author-email: Adam.Pluta@dlr.de
License: UNKNOWN
Platform: UNKNOWN
Classifier: License :: OSI Approved :: GNU General Public License v3 or later (GPLv3+)
Classifier: Programming Language :: Python :: 3
Classifier: Programming Language :: Python :: 3.6
Requires-Python: >=3.6
